MANIFEST.in
setup.py
Qtornado/README.md
Qtornado/__init__.py
Qtornado/db_manifest.py
Qtornado/init_filter.py
Qtornado/initial_content.py
Qtornado/lib.py
Qtornado/log.py
Qtornado/manifest.py
Qtornado/qtornado.py
Qtornado.egg-info/PKG-INFO
Qtornado.egg-info/SOURCES.txt
Qtornado.egg-info/dependency_links.txt
Qtornado.egg-info/entry_points.txt
Qtornado.egg-info/not-zip-safe
Qtornado.egg-info/requires.txt
Qtornado.egg-info/top_level.txt
Qtornado/db/__init__.py
Qtornado/db/sql.py
Qtornado/res/static/bootstrap/dist/css/bootstrap-theme.css
Qtornado/res/static/bootstrap/dist/css/bootstrap-theme.css.map
Qtornado/res/static/bootstrap/dist/css/bootstrap-theme.min.css
Qtornado/res/static/bootstrap/dist/css/bootstrap.css
Qtornado/res/static/bootstrap/dist/css/bootstrap.css.map
Qtornado/res/static/bootstrap/dist/css/bootstrap.min.css
Qtornado/res/static/bootstrap/dist/js/bootstrap.js
Qtornado/res/static/bootstrap/dist/js/bootstrap.min.js
Qtornado/res/static/bootstrap/grunt/bs-glyphicons-data-generator.js
Qtornado/res/static/bootstrap/grunt/bs-lessdoc-parser.js
Qtornado/res/static/bootstrap/grunt/bs-raw-files-generator.js
Qtornado/res/static/bootstrap/grunt/sauce_browsers.yml
Qtornado/res/static/bootstrap/js/affix.js
Qtornado/res/static/bootstrap/js/alert.js
Qtornado/res/static/bootstrap/js/button.js
Qtornado/res/static/bootstrap/js/carousel.js
Qtornado/res/static/bootstrap/js/collapse.js
Qtornado/res/static/bootstrap/js/dropdown.js
Qtornado/res/static/bootstrap/js/modal.js
Qtornado/res/static/bootstrap/js/popover.js
Qtornado/res/static/bootstrap/js/scrollspy.js
Qtornado/res/static/bootstrap/js/tab.js
Qtornado/res/static/bootstrap/js/tooltip.js
Qtornado/res/static/bootstrap/js/transition.js
Qtornado/res/static/bootstrap/less/alerts.less
Qtornado/res/static/bootstrap/less/badges.less
Qtornado/res/static/bootstrap/less/bootstrap.less
Qtornado/res/static/bootstrap/less/breadcrumbs.less
Qtornado/res/static/bootstrap/less/button-groups.less
Qtornado/res/static/bootstrap/less/buttons.less
Qtornado/res/static/bootstrap/less/carousel.less
Qtornado/res/static/bootstrap/less/close.less
Qtornado/res/static/bootstrap/less/code.less
Qtornado/res/static/bootstrap/less/component-animations.less
