Metadata-Version: 1.0
Name: Qtornado
Version: 3.2.1
Summary: a web framework like rails, which based on tornado
Home-page: https://github.com/Qingluan/QTornado.git
Author: Qing luan
Author-email: darkhackdevil@gmail.com
License: MIT
Platform: UNKNOWN
